Workbook

Sheet シミュレーション
B2: 収益シミュレーション — armtechstore.jp
B3: 作成日: 2026-07-02 ／ 下のシナリオ・料金プランを切り替えると全体が再計算されます
B5: シナリオ選択 | C5: 標準 | E5: 訪問数成長率/月 | F5: =INDEX('前提・根拠'!$C$13:$C$16,MATCH($C$5,'前提・根拠'!$B$13:$B$16,0)) | H5: 月額固定費 | I5: =INDEX('前提・根拠'!$C$20:$C$23,MATCH($C$6,'前提・根拠'!$B$20:$B$23,0))
B6: 料金プラン選択 | C6: 現行（月額55,000円） | E6: CVR | F6: =INDEX('前提・根拠'!$D$13:$D$16,MATCH($C$5,'前提・根拠'!$B$13:$B$16,0)) | H6: 売上レベシェア | I6: =INDEX('前提・根拠'!$D$20:$D$23,MATCH($C$6,'前提・根拠'!$B$20:$B$23,0))
E7: 平均購入単価 | F7: =INDEX('前提・根拠'!$E$13:$E$16,MATCH($C$5,'前提・根拠'!$B$13:$B$16,0)) | H7: 粗利レベシェア | I7: =INDEX('前提・根拠'!$E$20:$E$23,MATCH($C$6,'前提・根拠'!$B$20:$B$23,0))
E8: 粗利率 | F8: 0.49005788
C9: 実績 | I9: 予測
B10: 項目 | C10: 46023 | D10: 46054 | E10: 46082 | F10: 46113 | G10: 46143 | H10: 46174 | I10: 46204 | J10: 46235 | K10: 46266 | L10: 46296 | M10: 46327 | N10: 46357 | O10: 46388 | P10: 46419 | Q10: 46447 | R10: 46478 | S10: 46508 | T10: 46539 | U10: 予測12ヶ月計
B11: サイト訪問数 | C11: 5241 | D11: 5108 | E11: 7363 | F11: 6053 | G11: 5780 | H11: 5797 | I11: =ROUND(H11*(1+$F$5),0) | J11: =ROUND(I11*(1+$F$5),0) | K11: =ROUND(J11*(1+$F$5),0) | L11: =ROUND(K11*(1+$F$5),0) | M11: =ROUND(L11*(1+$F$5),0) | N11: =ROUND(M11*(1+$F$5),0) | O11: =ROUND(N11*(1+$F$5),0) | P11: =ROUND(O11*(1+$F$5),0) | ... T11: =ROUND(S11*(1+$F$5),0)
B12: 注文数 | C12: 4 | D12: 3 | E12: 3 | F12: 5 | G12: 3 | H12: 5 | I12: =I11*$F$6 | J12: =J11*$F$6 | K12: =K11*$F$6 | L12: =L11*$F$6 | M12: =M11*$F$6 | N12: =N11*$F$6 | O12: =O11*$F$6 | P12: =P11*$F$6 | ... T12: =T11*$F$6 | U12: =SUM(I12:T12)
B13: 売上 | C13: 54220 | D13: 26160 | E13: 23890 | F13: 115980 | G13: 36060 | H13: 72840 | I13: =I12*$F$7 | J13: =J12*$F$7 | K13: =K12*$F$7 | L13: =L12*$F$7 | M13: =M12*$F$7 | N13: =N12*$F$7 | O13: =O12*$F$7 | P13: =P12*$F$7 | ... T13: =T12*$F$7 | U13: =SUM(I13:T13)
B14: 粗利 | C14: 28630 | D14: 13080 | E14: 9223 | F14: 61116 | G14: 17530 | H14: 33200 | I14: =I13*$F$8 | J14: =J13*$F$8 | K14: =K13*$F$8 | L14: =L13*$F$8 | M14: =M13*$F$8 | N14: =N13*$F$8 | O14: =O13*$F$8 | P14: =P13*$F$8 | ... T14: =T13*$F$8 | U14: =SUM(I14:T14)
B15: CVR | C15: =IFERROR(C12/C11,0) | D15: =IFERROR(D12/D11,0) | E15: =IFERROR(E12/E11,0) | F15: =IFERROR(F12/F11,0) | G15: =IFERROR(G12/G11,0) | H15: =IFERROR(H12/H11,0) | I15: =$F$6 | J15: =$F$6 | K15: =$F$6 | L15: =$F$6 | M15: =$F$6 | N15: =$F$6 | O15: =$F$6 | P15: =$F$6 | ... T15: =$F$6
B16: 平均購入単価 | C16: =IFERROR(C13/C12,0) | D16: =IFERROR(D13/D12,0) | E16: =IFERROR(E13/E12,0) | F16: =IFERROR(F13/F12,0) | G16: =IFERROR(G13/G12,0) | H16: =IFERROR(H13/H12,0) | I16: =$F$7 | J16: =$F$7 | K16: =$F$7 | L16: =$F$7 | M16: =$F$7 | N16: =$F$7 | O16: =$F$7 | P16: =$F$7 | ... T16: =$F$7
B17: SEO費用 | C17: 55000 | D17: 55000 | E17: 55000 | F17: 55000 | G17: 55000 | H17: 55000 | I17: =$I$5+I13*$I$6+I14*$I$7 | J17: =$I$5+J13*$I$6+J14*$I$7 | K17: =$I$5+K13*$I$6+K14*$I$7 | L17: =$I$5+L13*$I$6+L14*$I$7 | M17: =$I$5+M13*$I$6+M14*$I$7 | N17: =$I$5+N13*$I$6+N14*$I$7 | O17: =$I$5+O13*$I$6+O14*$I$7 | P17: =$I$5+P13*$I$6+P14*$I$7 | ... T17: =$I$5+T13*$I$6+T14*$I$7 | U17: =SUM(I17:T17)
B18: 手残り（粗利−費用） | C18: =C14-C17 | D18: =D14-D17 | E18: =E14-E17 | F18: =F14-F17 | G18: =G14-G17 | H18: =H14-H17 | I18: =I14-I17 | J18: =J14-J17 | ... T18: =T14-T17 | U18: =SUM(I18:T18)
B19: 累計手残り | C19: =C18 | D19: =C19+D18 | E19: =D19+E18 | F19: =E19+F18 | G19: =F19+G18 | H19: =G19+H18 | I19: =H19+I18 | J19: =I19+J18 | K19: =J19+K18 | ... T19: =S19+T18
B21: ※実績列（灰色）は確定値。予測列はシナリオパラメータに連動する数式です。レンジ（P10〜P90）は「モンテカルロ」シートをご参照ください。

Sheet シナリオ比較
B2: シナリオ比較（2026/07〜2027/06）
B4: 【保守】 成長率1.0%/月・CVR 0.045%・単価¥12,000 — 成長鈍化・CVR横ばい（CI下限）
B5: 項目 | C5: 46204 | D5: 46235 | E5: 46266 | F5: 46296 | G5: 46327 | H5: 46357 | I5: 46388 | J5: 46419 | K5: 46447 | L5: 46478 | M5: 46508 | N5: 46539 | O5: 12ヶ月計
B6: サイト訪問数 | C6: 5855 | D6: 5914 | E6: 5973 | F6: 6032 | G6: 6093 | H6: 6154 | I6: 6215 | J6: 6277 | K6: 6340 | L6: 6403 | M6: 6468 | N6: 6532
B7: 注文数 | C7: 2.63 | D7: 2.66 | E7: 2.69 | F7: 2.71 | G7: 2.74 | H7: 2.77 | I7: 2.8 | J7: 2.82 | K7: 2.85 | L7: 2.88 | M7: 2.91 | N7: 2.94
B8: 売上 | C8: 31617 | D8: 31933 | E8: 32252 | F8: 32575 | G8: 32901 | H8: 33230 | I8: 33562 | J8: 33898 | K8: 34237 | L8: 34579 | M8: 34925 | N8: 35274 | O8: 400983
B9: 粗利 | C9: 15492 | D9: 15647 | E9: 15804 | F9: 15962 | G9: 16121 | H9: 16283 | I9: 16445 | J9: 16610 | K9: 16776 | L9: 16944 | M9: 17113 | N9: 17284 | O9: 196481
B11: 【標準】 成長率2.5%/月・CVR 0.065%・単価¥14,000 — 直近実績の成長・CVRを維持
B12: 項目 | C12: 46204 | D12: 46235 | E12: 46266 | F12: 46296 | G12: 46327 | H12: 46357 | I12: 46388 | J12: 46419 | K12: 46447 | L12: 46478 | M12: 46508 | N12: 46539 | O12: 12ヶ月計
B13: サイト訪問数 | C13: 5942 | D13: 6090 | E13: 6243 | F13: 6399 | G13: 6559 | H13: 6723 | I13: 6891 | J13: 7063 | K13: 7240 | L13: 7421 | M13: 7606 | N13: 7796
B14: 注文数 | C14: 3.86 | D14: 3.96 | E14: 4.06 | F14: 4.16 | G14: 4.26 | H14: 4.37 | I14: 4.48 | J14: 4.59 | K14: 4.71 | L14: 4.82 | M14: 4.94 | N14: 5.07
B15: 売上 | C15: 54072 | D15: 55423 | E15: 56809 | F15: 58229 | G15: 59685 | H15: 61177 | I15: 62706 | J15: 64274 | K15: 65881 | L15: 67528 | M15: 69216 | N15: 70947 | O15: 745947
B16: 粗利 | C16: 26495 | D16: 27157 | E16: 27836 | F16: 28532 | G16: 29246 | H16: 29977 | I16: 30726 | J16: 31494 | K16: 32282 | L16: 33089 | M16: 33916 | N16: 34764 | O16: 365514
B18: 【強気】 成長率5.0%/月・CVR 0.090%・単価¥15,000 — KW順位改善+CVR施策が奏功（CI上限）
B19: 項目 | C19: 46204 | D19: 46235 | E19: 46266 | F19: 46296 | G19: 46327 | H19: 46357 | I19: 46388 | J19: 46419 | K19: 46447 | L19: 46478 | M19: 46508 | N19: 46539 | O19: 12ヶ月計
B20: サイト訪問数 | C20: 6087 | D20: 6391 | E20: 6711 | F20: 7046 | G20: 7399 | H20: 7769 | I20: 8157 | J20: 8565 | K20: 8993 | L20: 9443 | M20: 9915 | N20: 10411
B21: 注文数 | C21: 5.48 | D21: 5.75 | E21: 6.04 | F21: 6.34 | G21: 6.66 | H21: 6.99 | I21: 7.34 | J21: 7.71 | K21: 8.09 | L21: 8.5 | M21: 8.92 | N21: 9.37
B22: 売上 | C22: 82172 | D22: 86281 | E22: 90595 | F22: 95125 | G22: 99881 | H22: 104875 | I22: 110119 | J22: 115625 | K22: 121406 | L22: 127476 | M22: 133850 | N22: 140543 | O22: 1307948
B23: 粗利 | C23: 40265 | D23: 42278 | E23: 44392 | F23: 46611 | G23: 48942 | H23: 51389 | I23: 53958 | J23: 56656 | K23: 59489 | L23: 62463 | M23: 65587 | N23: 68866 | O23: 640896
B25: 料金プラン別 クライアント手残り（12ヶ月累計 = 粗利 − SEO費用）
B26: プラン ＼ シナリオ | C26: 保守 | D26: 標準 | E26: 強気
B27: 現行: 月額55,000円 | C27: -463519 | D27: -294486 | E27: -19104
B28: 提案: 月額88,000円+売上5% | C28: -879569 | D28: -727782 | E28: -480502
B29: 希望: 粗利レベシェア50% | C29: 98240 | D29: 182756 | E29: 320448
B31: ※粗利レベシェア50%案は費用が粗利に連動するため、クライアント手残りは常に粗利の50%（マイナスにならない）。固定費型プランは粗利が費用を下回る月は持ち出しになります。

Sheet モンテカルロ
B2: モンテカルロ・シミュレーション（各月2万回試行）
B3: 注文数〜Poisson(訪問数×CVR)、注文単価〜対数正規（実測フィット）。売上・粗利の振れ幅を示します。
B5: 【保守】
B6: 項目 | C6: 46204 | D6: 46235 | E6: 46266 | F6: 46296 | G6: 46327 | H6: 46357 | I6: 46388 | J6: 46419 | K6: 46447 | L6: 46478 | M6: 46508 | N6: 46539
B7: 売上 P90（上振れ） | C7: 58969.279 | D7: 59565.118 | E7: 60835.49 | F7: 61028.749 | G7: 61493.026 | H7: 62005.055 | I7: 62509.803 | J7: 62742.076 | K7: 63419.262 | L7: 64007.429 | M7: 64501.334 | N7: 64382.147
B8: 売上 P50（中央値） | C8: 28937.758 | D8: 29345.318 | E8: 29615.053 | F8: 29957.249 | G8: 30557.047 | H8: 30933.247 | I8: 30841.149 | J8: 31503.813 | K8: 31637.563 | L8: 32042.325 | M8: 32323.436 | N8: 32538.029
B9: 売上 P10（下振れ） | C9: 7706.1483 | D9: 7926.6033 | E9: 8307.8406 | F9: 8218.6948 | G9: 8568.185 | H9: 8838.4787 | I9: 8533.2188 | J9: 8879.0756 | K9: 9205.2074 | L9: 9282.8221 | M9: 9514.7069 | N9: 9414.5647
B10: 粗利 P50 | C10: 14179.501 | D10: 14379.206 | E10: 14511.376 | F10: 14679.052 | G10: 14972.953 | H10: 15157.291 | I10: 15112.163 | J10: 15436.868 | K10: 15502.406 | L10: 15700.739 | M10: 15838.484 | N10: 15943.634
B11: 粗利≧55,000円の確率 | C11: 0.0011 | D11: 0.0016 | E11: 0.0016 | F11: 0.0015 | G11: 0.0022 | H11: 0.00215 | I11: 0.0025 | J11: 0.00215 | K11: 0.0017 | L11: 0.00225 | M11: 0.00295 | N11: 0.00215
B13: 【標準】
B14: 項目 | C14: 46204 | D14: 46235 | E14: 46266 | F14: 46296 | G14: 46327 | H14: 46357 | I14: 46388 | J14: 46419 | K14: 46447 | L14: 46478 | M14: 46508 | N14: 46539
B15: 売上 P90（上振れ） | C15: 92615.509 | D15: 95250.774 | E15: 97975.966 | F15: 98621.187 | G15: 100588.5 | H15: 102575.53 | I15: 103966.97 | J15: 106720.53 | K15: 108556.48 | L15: 110863.24 | M15: 112617.83 | N15: 114901.54
B16: 売上 P50（中央値） | C16: 51225.215 | D16: 52241.378 | E16: 54124.568 | F16: 54858.375 | G16: 56412.073 | H16: 58228.022 | I16: 59320.4 | J16: 61387.067 | K16: 62620.682 | L16: 64854.476 | M16: 66281.997 | N16: 67409.871
B17: 売上 P10（下振れ） | C17: 18835.384 | D17: 19686.557 | E17: 21218.495 | F17: 21740.516 | G17: 22690.248 | H17: 23153.12 | I17: 24277.423 | J17: 25369.344 | K17: 26558.566 | L17: 27626.882 | M17: 28654.973 | N17: 30062.399
B18: 粗利 P50 | C18: 25100.355 | D18: 25598.275 | E18: 26521.039 | F18: 26880.604 | G18: 27641.916 | H18: 28531.731 | I18: 29066.996 | J18: 30079.663 | K18: 30684.134 | L18: 31778.693 | M18: 32478.178 | N18: 33030.837
B19: 粗利≧55,000円の確率 | C19: 0.03555 | D19: 0.04145 | E19: 0.0511 | F19: 0.05135 | G19: 0.05585 | H19: 0.06265 | I19: 0.0692 | J19: 0.07615 | K19: 0.083 | L19: 0.0941 | M19: 0.1021 | N19: 0.11195
B21: 【強気】
B22: 項目 | C22: 46204 | D22: 46235 | E22: 46266 | F22: 46296 | G22: 46327 | H22: 46357 | I22: 46388 | J22: 46419 | K22: 46447 | L22: 46478 | M22: 46508 | N22: 46539
B23: 売上 P90（上振れ） | C23: 131029.76 | D23: 136898.76 | E23: 142989.56 | F23: 149139.75 | G23: 155609.03 | H23: 160844.97 | I23: 167290.77 | J23: 175099.52 | K23: 182169.96 | L23: 188925.46 | M23: 198263.54 | N23: 206411.3
B24: 売上 P50（中央値） | C24: 78719.035 | D24: 83411.75 | E24: 86833.643 | F24: 92199.368 | G24: 96291.231 | H24: 101668.71 | I24: 107020.53 | J24: 113090.42 | K24: 118364.78 | L24: 123976.36 | M24: 130753.17 | N24: 137972.14
B25: 売上 P10（下振れ） | C25: 36507.697 | D25: 39443.297 | E25: 42489.452 | F25: 46319.286 | G25: 49034.457 | H25: 53118.651 | I25: 57149.711 | J25: 61290.201 | K25: 65148.371 | L25: 70424.207 | M25: 75829.045 | N25: 79111.722
B26: 粗利 P50 | C26: 38572.327 | D26: 40871.757 | E26: 42548.485 | F26: 45177.691 | G26: 47182.703 | H26: 49817.668 | I26: 52440.058 | J26: 55414.308 | K26: 57998.744 | L26: 60748.419 | M26: 64069.054 | N26: 67606.35
B27: 粗利≧55,000円の確率 | C27: 0.20495 | D27: 0.23595 | E27: 0.26985 | F27: 0.31475 | G27: 0.3524 | H27: 0.4045 | I27: 0.4545 | J27: 0.5071 | K27: 0.55545 | L27: 0.60345 | M27: 0.6599 | N27: 0.70335

Sheet 実績データ
B2: 月次実績（2025/03〜2026/06）
B4: 年月 | C4: サイト訪問数 | D4: 注文数 | E4: 売上 | F4: 粗利 | G4: CVR | H4: 平均購入単価 | I4: 粗利率
B5: 45717 | C5: 679 | D5: 0 | E5: 0 | F5: 0 | G5: =IFERROR(D5/C5,0) | H5: =IFERROR(E5/D5,0) | I5: =IFERROR(F5/E5,0)
B6: 45748 | C6: 44 | D6: 0 | E6: 0 | F6: 0 | G6: =IFERROR(D6/C6,0) | H6: =IFERROR(E6/D6,0) | I6: =IFERROR(F6/E6,0)
B7: 45778 | C7: 90 | D7: 0 | E7: 0 | F7: 0 | G7: =IFERROR(D7/C7,0) | H7: =IFERROR(E7/D7,0) | I7: =IFERROR(F7/E7,0)
B8: 45809 | C8: 119 | D8: 0 | E8: 0 | F8: 0 | G8: =IFERROR(D8/C8,0) | H8: =IFERROR(E8/D8,0) | I8: =IFERROR(F8/E8,0)
B9: 45839 | C9: 112 | D9: 0 | E9: 0 | F9: 0 | G9: =IFERROR(D9/C9,0) | H9: =IFERROR(E9/D9,0) | I9: =IFERROR(F9/E9,0)
B10: 45870 | C10: 197 | D10: 0 | E10: 0 | F10: 0 | G10: =IFERROR(D10/C10,0) | H10: =IFERROR(E10/D10,0) | I10: =IFERROR(F10/E10,0)
B11: 45901 | C11: 597 | D11: 3 | E11: 42780 | F11: 20390 | G11: =IFERROR(D11/C11,0) | H11: =IFERROR(E11/D11,0) | I11: =IFERROR(F11/E11,0)
B12: 45931 | C12: 1153 | D12: 1 | E12: 9880 | F12: 3940 | G12: =IFERROR(D12/C12,0) | H12: =IFERROR(E12/D12,0) | I12: =IFERROR(F12/E12,0)
B13: 45962 | C13: 2015 | D13: 0 | E13: 0 | F13: 0 | G13: =IFERROR(D13/C13,0) | H13: =IFERROR(E13/D13,0) | I13: =IFERROR(F13/E13,0)
B14: 45992 | C14: 3111 | D14: 0 | E14: 0 | F14: 0 | G14: =IFERROR(D14/C14,0) | H14: =IFERROR(E14/D14,0) | I14: =IFERROR(F14/E14,0)
B15: 46023 | C15: 5241 | D15: 4 | E15: 54220 | F15: 28630 | G15: =IFERROR(D15/C15,0) | H15: =IFERROR(E15/D15,0) | I15: =IFERROR(F15/E15,0)
B16: 46054 | C16: 5108 | D16: 3 | E16: 26160 | F16: 13080 | G16: =IFERROR(D16/C16,0) | H16: =IFERROR(E16/D16,0) | I16: =IFERROR(F16/E16,0)
... B20: 46174 | C20: 5797 | D20: 5 | E20: 72840 | F20: 33200 | G20: =IFERROR(D20/C20,0) | H20: =IFERROR(E20/D20,0) | I20: =IFERROR(F20/E20,0)
B21: 合計/平均 | C21: =SUM(C5:C20) | D21: =SUM(D5:D20) | E21: =SUM(E5:E20) | F21: =SUM(F5:F20) | G21: =D21/C21 | H21: =E21/D21 | I21: =F21/E21

Sheet 前提・根拠
B2: 前提条件とパラメータ推定根拠
B4: 実測パラメータ（2025/09〜2026/06 プール推定）
B5: CVR（購入率） | C5: 0.00063953764 | D5: 注文27件 ÷ 訪問42,218（95%信頼区間 0.044%〜0.093%）
B6: 平均購入単価 | C6: 14141.111 | D6: 売上¥381,810 ÷ 27件（月次実績は¥7,963〜¥23,196と分散大）
B7: 粗利率 | C7: 0.49005788 | D7: 粗利¥187,109 ÷ 売上¥381,810
B8: 直近6ヶ月のトラフィック月次成長率 | C8: 0.020370345 | D8: 2026/01: 5,241 → 2026/06: 5,797（幾何平均）
B9: KW順位からの流入ポテンシャル | C9: 1.48 | D9: 追跡506KW中155KWが200位以内。CTRカーブ推定で現状1,799クリック/月→順位1段改善で2,657クリック/月
B11: シナリオ別パラメータ（シミュレーションシートのドロップダウンと連動）
B12: シナリオ | C12: 訪問数成長率/月 | D12: CVR | E12: 平均購入単価 | F12: 根拠
B13: 保守 | C13: 0.01 | D13: 0.00045 | E13: 12000 | F13: 成長が鈍化しCVRは信頼区間の下限で推移
B14: 標準 | C14: 0.025 | D14: 0.00065 | E14: 14000 | F14: 直近実績の成長率+施策効果、CVR・単価は実測値を維持
B15: 強気 | C15: 0.05 | D15: 0.0009 | E15: 15000 | F15: KW順位改善(+48%流入余地)とCVR改善施策が奏功、CVRは信頼区間上限
B16: カスタム | C16: 0.03 | D16: 0.0007 | E16: 14000 | F16: 自由に編集してください
B18: 料金プラン（シミュレーションシートのドロップダウンと連動）
B19: プラン | C19: 月額固定費 | D19: 売上レベシェア | E19: 粗利レベシェア | F19: 備考
B20: 現行（月額55,000円） | C20: 55000 | D20: 0 | E20: 0 | F20: 現行契約
B21: 提案（月額88,000円+売上5%） | C21: 88000 | D21: 0.05 | E21: 0 | F21: 20260629シート記載の提案プラン
B22: 希望（粗利レベシェア50%） | C22: 0 | D22: 0 | E22: 0.5 | F22: クライアント希望案。固定費ゼロ
B23: カスタム | C23: 55000 | D23: 0 | E23: 0 | F23: 自由に編集してください
B25: 【手法】
B26: ・予測式: 訪問数[t] = 訪問数[t-1] × (1+成長率) / 注文数 = 訪問数 × CVR / 売上 = 注文数 × 平均単価 / 粗利 = 売上 × 粗利率
B27: ・モンテカルロ: 注文数〜Poisson(訪問数×CVR)、注文単価〜対数正規（実測月次単価にフィット）、各月2万回試行
B28: ・注文数が月3〜5件と少なくCVR推定の不確実性が大きいため、点推定ではなくP10〜P90のレンジで併記
B30: 【元シミュレーションからの主な変更点】
B31: ・CVR想定 0.10%→0.15% は実測95%信頼区間（0.044%〜0.093%）を大きく超えるため、実測ベースに補正
B32: ・平均単価 ¥13,000 → 実測 ¥14,141 ベースに更新（¥14,000）
B33: ・粗利率 50% → 実測 49.0%
B34: ・トラフィック成長 110%/月 は直近実測（+2.0%/月）と乖離が大きいため、シナリオ別に 1%/2.5%/5% に補正
B36: 【注意事項】
B37: ※本数値は現時点の実績（注文27件）をもとに算出した概算シミュレーションです。
B38: ※注文数のサンプルが少ないため、実際の売上は月次でP10〜P90レンジ程度の振れが想定されます。
... B40: ※今後の方向性や検討材料の一つとしてご参照いただくことを目的とした資料です。
